rfc3987.py
rfc3987-1.3.6.dist-info/metadata.json
rfc3987-1.3.6.dist-info/DESCRIPTION.rst
rfc3987-1.3.6.dist-info/METADATA
rfc3987-1.3.6.dist-info/top_level.txt
rfc3987-1.3.6.dist-info/WHEEL
rfc3987-1.3.6.dist-info/RECORD
