Metadata-Version: 2.0
Name: rfc3987
Version: 1.3.6
Summary: Parsing and validation of URIs (RFC 3986) and IRIs (RFC 3987)
Home-page: http://pypi.python.org/pypi/rfc3987
Author: Daniel Gerber
Author-email: daniel.g.gerber@gmail.com
License: GNU GPLv3+
Download-URL: https://github.com/dgerber/rfc3987
Keywords: URI IRI URL rfc3986 rfc3987 validation
Platform: UNKNOWN
Classifier: Development Status :: 5 - Production/Stable
Classifier: Intended Audience :: Developers
Classifier: License :: OSI Approved :: GNU General Public License v3 or later (GPLv3+)
Classifier: Operating System :: OS Independent
Classifier: Programming Language :: Python
Classifier: Programming Language :: Python :: 2
Classifier: Programming Language :: Python :: 2.6
Classifier: Programming Language :: Python :: 2.7
Classifier: Programming Language :: Python :: 3
Classifier: Programming Language :: Python :: 3.2
Classifier: Programming Language :: Python :: 3.3
Classifier: Programming Language :: Python :: 3.4
Classifier: Programming Language :: Python :: 3.5
Classifier: Topic :: Internet
